aioipfs/__init__.py
aioipfs/api.py
aioipfs/exceptions.py
aioipfs/helpers.py
aioipfs/multi.py
aioipfs/util.py
aioipfs/apis/__init__.py
aioipfs/apis/dag.py
aioipfs/apis/multibase.py
aioipfs/apis/p2p.py
aioipfs/apis/pin.py
aioipfs/apis/pubsub.py
aioipfs/apis/swarm.py
aioipfs/scripts/__init__.py
aioipfs/scripts/bohort/__init__.py
aioipfs/scripts/bohort/cli.py
aioipfs/scripts/bohort/default_config.yaml
aioipfs-0.7.1.dist-info/LICENSE
aioipfs-0.7.1.dist-info/METADATA
aioipfs-0.7.1.dist-info/WHEEL
aioipfs-0.7.1.dist-info/entry_points.txt
aioipfs-0.7.1.dist-info/top_level.txt
aioipfs-0.7.1.dist-info/RECORD
