Metadata-Version: 2.1
Name: aioipfs
Version: 0.7.1
Summary: Asynchronous IPFS client library
Author-email: cipres <alkaline@gmx.co.uk>
License: LGPLv3
Project-URL: Homepage, https://gitlab.com/cipres/aioipfs
Keywords: asyncio,aiohttp,ipfs
Classifier: Programming Language :: Python
Classifier: Programming Language :: Python :: 3.6
Classifier: Programming Language :: Python :: 3.7
Classifier: Programming Language :: Python :: 3.8
Classifier: Programming Language :: Python :: 3.9
Classifier: Programming Language :: Python :: 3.10
Classifier: Programming Language :: Python :: 3.11
Classifier: Programming Language :: Python :: 3.12
Classifier: Intended Audience :: Developers
Classifier: Development Status :: 5 - Production/Stable
Classifier: Natural Language :: English
Classifier: Operating System :: OS Independent
Classifier: License :: OSI Approved :: GNU Lesser General Public License v3 (LGPLv3)
Classifier: Topic :: System :: Filesystems
Classifier: Topic :: Communications :: File Sharing
License-File: LICENSE
Requires-Dist: aiohttp >=3.7.4
Requires-Dist: aiofiles >=0.7.0
Requires-Dist: async-timeout >=4.0.3
Requires-Dist: base58 >=1.0.2
Requires-Dist: gitignore-parser ==0.1.9
Requires-Dist: multiaddr >=0.0.9
Requires-Dist: py-multibase >=1.0.3
Requires-Dist: py-multiformats-cid >=0.4.3
Requires-Dist: setuptools >=67.7.0
Provides-Extra: bohort
Requires-Dist: appdirs >=1.4.4 ; extra == 'bohort'
Requires-Dist: omegaconf ==2.3.0 ; extra == 'bohort'
Requires-Dist: ptpython-aioipfs >=3.0.27 ; extra == 'bohort'
Provides-Extra: car
Requires-Dist: ipfs-car-decoder ==0.1.1 ; extra == 'car'
Provides-Extra: dev
Requires-Dist: mypy ; extra == 'dev'
Requires-Dist: pytest ; extra == 'dev'
Requires-Dist: pytest-asyncio ; extra == 'dev'
Requires-Dist: pytest-cov ; extra == 'dev'
Requires-Dist: tox ; extra == 'dev'
Requires-Dist: flake8 ; extra == 'dev'
Requires-Dist: wheel ; extra == 'dev'
Provides-Extra: docs
Requires-Dist: sphinx ==5.3.0 ; extra == 'docs'
Requires-Dist: sphinxcontrib-asyncio ; extra == 'docs'
Requires-Dist: sphinxcontrib-video ; extra == 'docs'
Requires-Dist: guzzle-sphinx-theme ; extra == 'docs'
Provides-Extra: orjson
Requires-Dist: orjson >=3.0 ; extra == 'orjson'
